CITATION
LICENSE
MANIFEST.in
README.rst
setup.py
./PyMaple.egg-info/PKG-INFO
./PyMaple.egg-info/SOURCES.txt
./PyMaple.egg-info/dependency_links.txt
./PyMaple.egg-info/requires.txt
./PyMaple.egg-info/top_level.txt
./maple/__init__.py
./maple/__meta__.py
./maple/api/__init__.py
./maple/api/_container.py
./maple/api/_image.py
./maple/api/_maple.py
./maple/backend/__init__.py
./maple/backend/_backend.py
./maple/backend/docker/__init__.py
./maple/backend/docker/container.py
./maple/backend/docker/image.py
./maple/backend/docker/system.py
./maple/backend/podman/__init__.py
./maple/backend/podman/container.py
./maple/backend/podman/image.py
./maple/backend/podman/system.py
./maple/backend/singularity/__init__.py
./maple/backend/singularity/container.py
./maple/backend/singularity/image.py
./maple/backend/singularity/system.py
./maple/cli/__init__.py
./maple/cli/_container.py
./maple/cli/_image.py
./maple/cli/_maple.py
./maple/cli/_system.py
./maple/resources/__init__.py
maple/maple
maple/resources/Dockerfile.base
maple/resources/Dockerfile.mpi
maple/resources/Dockerfile.root
maple/resources/Dockerfile.user
maple/resources/__init__.py
media/icon.svg
media/maple-use-1.png
media/maple-use-2.png