Metadata-Version: 1.1
Name: PyMaple
Version: 2.2
Summary: Maple Container Utility
Home-page: UNKNOWN
Author: Akash Dhruv
Author-email: UNKNOWN
License: MIT License
Platform: UNKNOWN
Classifier: Programming Language :: Python :: 3.8
Classifier: License :: OSI Approved :: MIT License
